airpollutionwatch/TM20210000.py
airpollutionwatch/__init__.py
airpollutionwatch/amedas.py
airpollutionwatch/chiba.py
airpollutionwatch/convert.py
airpollutionwatch/kanagawa.py
airpollutionwatch/shizuoka.py
airpollutionwatch/tokyo.py
airpollutionwatch/yamanashi.py
airpollutionwatch-0.1.5.dist-info/LICENSE
airpollutionwatch-0.1.5.dist-info/METADATA
airpollutionwatch-0.1.5.dist-info/WHEEL
airpollutionwatch-0.1.5.dist-info/RECORD
