Metadata-Version: 2.1
Name: airpollutionwatch
Version: 0.1.5
Summary: 
Author: vitroid
Author-email: vitroid@gmail.com
Requires-Python: >=3.10,<4.0
Classifier: Programming Language :: Python :: 3
Classifier: Programming Language :: Python :: 3.10
Classifier: Programming Language :: Python :: 3.11
Classifier: Programming Language :: Python :: 3.12
Requires-Dist: lxml (>=5.2.2,<6.0.0)
Requires-Dist: pandas (>=2.2.2,<3.0.0)
Requires-Dist: requests (>=2.32.3,<3.0.0)
Requires-Dist: requests-cache (>=1.2.1,<2.0.0)
